MANIFEST.in
README.md
setup.py
src/contrive.egg-info/PKG-INFO
src/contrive.egg-info/SOURCES.txt
src/contrive.egg-info/dependency_links.txt
src/contrive.egg-info/entry_points.txt
src/contrive.egg-info/requires.txt
src/contrive.egg-info/top_level.txt
src/masoniteorm/__init__.py
src/masoniteorm/exceptions.py
src/masoniteorm/collection/Collection.py
src/masoniteorm/collection/__init__.py
src/masoniteorm/commands/Entry.py
src/masoniteorm/commands/MakeMigrationCommand.py
src/masoniteorm/commands/MakeSeedCommand.py
src/masoniteorm/commands/MigrateCommand.py
src/masoniteorm/commands/MigrateRefreshCommand.py
src/masoniteorm/commands/MigrateRollbackCommand.py
src/masoniteorm/commands/SeedRunCommand.py
src/masoniteorm/commands/__init__.py
src/masoniteorm/connections/BaseConnection.py
src/masoniteorm/connections/ConnectionFactory.py
src/masoniteorm/connections/ConnectionResolver.py
src/masoniteorm/connections/MSSQLConnection.py
src/masoniteorm/connections/MySQLConnection.py
src/masoniteorm/connections/PostgresConnection.py
src/masoniteorm/connections/SQLiteConnection.py
src/masoniteorm/connections/__init__.py
src/masoniteorm/expressions/expressions.py
src/masoniteorm/factories/Factory.py
src/masoniteorm/factories/__init__.py
src/masoniteorm/migrations/Migration.py
src/masoniteorm/migrations/__init__.py
src/masoniteorm/models/MigrationModel.py
src/masoniteorm/models/Model.py
src/masoniteorm/models/__init__.py
src/masoniteorm/query/QueryBuilder.py
src/masoniteorm/query/__init__.py
src/masoniteorm/query/grammars/BaseGrammar.py
src/masoniteorm/query/grammars/GrammarFactory.py
src/masoniteorm/query/grammars/MSSQLGrammar.py
src/masoniteorm/query/grammars/MySQLGrammar.py
src/masoniteorm/query/grammars/PostgresGrammar.py
src/masoniteorm/query/grammars/SQLiteGrammar.py
src/masoniteorm/query/grammars/__init__.py
src/masoniteorm/query/processors/MySQLPostProcessor.py
src/masoniteorm/query/processors/PostProcessorFactory.py
src/masoniteorm/query/processors/PostgresPostProcessor.py
src/masoniteorm/query/processors/SQLitePostProcessor.py
src/masoniteorm/query/processors/__init__.py
src/masoniteorm/relationships/BaseRelationship.py
src/masoniteorm/relationships/BelongsTo.py
